gutt/__init__.py
gutt/_meta.py
gutt/cli/__init__.py
gutt/cli/main.py
gutt/model.py
gutt/template.py
gutt/utils.py
gutt-1.2.0.dist-info/LICENSE
gutt-1.2.0.dist-info/METADATA
gutt-1.2.0.dist-info/WHEEL
gutt-1.2.0.dist-info/entry_points.txt
gutt-1.2.0.dist-info/RECORD
