Metadata-Version: 2.1
Name: gutt
Version: 1.2.0
Summary: Auto generate unit test templates
Home-page: https://github.com/ryanchao2012/gutt
License: MIT
Author: Ryan
Author-email: ryanchao2012@gmail.com
Requires-Python: >=3.7,<4.0
Classifier: License :: OSI Approved :: MIT License
Classifier: Programming Language :: Python :: 3
Classifier: Programming Language :: Python :: 3.7
Classifier: Programming Language :: Python :: 3.8
Classifier: Programming Language :: Python :: 3.9
Classifier: Programming Language :: Python :: 3.10
Classifier: Programming Language :: Python :: 3.11
Classifier: Programming Language :: Python :: 3.12
Classifier: Programming Language :: Python :: 3.13
Requires-Dist: black
Requires-Dist: cattrs
Requires-Dist: click
Requires-Dist: isort
Requires-Dist: libcst
Project-URL: Repository, https://github.com/ryanchao2012/gutt
